eyefeatures/__init__.py
eyefeatures/deep/__init__.py
eyefeatures/deep/datasets.py
eyefeatures/deep/models.py
eyefeatures/features/__init__.py
eyefeatures/features/complex.py
eyefeatures/features/extractor.py
eyefeatures/features/measures.py
eyefeatures/features/scanpath_complex.py
eyefeatures/features/scanpath_dist.py
eyefeatures/features/shift.py
eyefeatures/features/stats.py
eyefeatures/preprocessing/__init__.py
eyefeatures/preprocessing/_utils.py
eyefeatures/preprocessing/aoi_extraction.py
eyefeatures/preprocessing/base.py
eyefeatures/preprocessing/blinks_extraction.py
eyefeatures/preprocessing/fixation_extraction.py
eyefeatures/preprocessing/smoothing.py
eyefeatures/utils.py
eyefeatures/visualization/__init__.py
eyefeatures/visualization/dynamic_visualization.py
eyefeatures/visualization/static_visualization.py
eyefeatures-1.0.1.dist-info/LICENSE
eyefeatures-1.0.1.dist-info/METADATA
eyefeatures-1.0.1.dist-info/WHEEL
eyefeatures-1.0.1.dist-info/RECORD
