Metadata-Version: 2.3
Name: eyefeatures
Version: 1.0.1
Summary: Preprocessing, visualization, statistical analysis, feature engineering, and machine learning of eye movement data.
License: MIT License
Author: Kondaurov Zakhar
Requires-Python: >=3.12,<3.13
Classifier: License :: Other/Proprietary License
Classifier: Programming Language :: Python :: 3
Classifier: Programming Language :: Python :: 3.12
Requires-Dist: EMD-signal (==1.6.4)
Requires-Dist: gudhi (==3.10.1)
Requires-Dist: matplotlib (==3.8.4)
Requires-Dist: numba (==0.60.0)
Requires-Dist: numpy (==1.26.0)
Requires-Dist: pandas (==2.2.2)
Requires-Dist: scikit-learn (==1.5.1)
Requires-Dist: scikit_multilearn (==0.2.0)
Requires-Dist: scipy (==1.14.1)
Requires-Dist: tqdm (==4.66.4)
